stash_service.py
stash_service-1.1.3.dist-info/METADATA
stash_service-1.1.3.dist-info/WHEEL
stash_service-1.1.3.dist-info/top_level.txt
stash_service-1.1.3.dist-info/RECORD
