Metadata-Version: 2.1
Name: stash-service
Version: 1.1.3
Summary: A PyPI packages that supports all the necessary error codes, validation exception, common exceptions of a webservice. This PyPI package includes a method that establishes the connection to your firebase account and provides logging methods.
Home-page: UNKNOWN
Author: Maria Irudaya Regilan J, Pavithra K, Venkateshwar S, D Vidhyalakshmi
Author-email: britsa.tech@gmail.com
License: UNKNOWN
Platform: UNKNOWN
Classifier: Programming Language :: Python :: 3.6
Classifier: Programming Language :: Python :: 3.7
Classifier: Programming Language :: Python :: 3.8
Classifier: Programming Language :: Python :: 3.9
Classifier: Operating System :: OS Independent
Requires-Dist: firebase-admin
